discordce/exceptions.py
discordce/__init__.py
discordce/__main__.py
discordce-0.1.dist-info/DESCRIPTION.rst
discordce-0.1.dist-info/entry_points.txt
discordce-0.1.dist-info/METADATA
discordce-0.1.dist-info/metadata.json
discordce-0.1.dist-info/RECORD
discordce-0.1.dist-info/top_level.txt
discordce-0.1.dist-info/WHEEL
