Metadata-Version: 2.0
Name: discordce
Version: 0.1
Summary: Append .png to cached discord data files.
Home-page: https://github.com/Slyyxp/Discord-Cache-Exporter
Author: Slyyxp
Author-email: slyyxp@protonmail.com
License: UNKNOWN
Platform: UNKNOWN
Classifier: Programming Language :: Python :: 3.8
